{
    "\/admin\/includes\/classes\/screen\/points\/types.php": {
        "jQuery( document ).ready( function ( $ ) {\n\n\t\t\t\t$( '.if-js-closed' )\n\t\t\t\t\t.removeClass( 'if-js-closed' )\n\t\t\t\t\t.addClass( 'closed' );\n\n\t\t\t\tpostboxes.add_postbox_toggles(": {
            "91": false
        },
        ");\n\t\t\t} );": {
            "101": false
        },
        "points-": {
            "259": {
                "name": "array",
                "type": "unknown",
                "args_started": true,
                "arg_count": 0,
                "parentheses": 1
            }
        },
        "-save": {
            "259": {
                "name": "array",
                "type": "unknown",
                "args_started": true,
                "arg_count": 0,
                "parentheses": 1
            }
        },
        "WordPointsHooksAdminData.events[": {
            "341": false
        },
        "] =": {
            "344": false
        },
        ";\n\t\t\tWordPointsHooksAdminData.reactions[": {
            "343": false
        },
        ";": {
            "344": false
        },
        "1": {
            "566": false
        },
        "2": {
            "566": false
        }
    },
    "\/admin\/includes\/classes\/screen.php": {
        "<!-- .wrap -->": {
            "110": false
        }
    },
    "\/admin\/includes\/functions.php": {
        "display": {
            "53": {
                "name": "array",
                "type": "unknown",
                "args_started": true,
                "arg_count": 1,
                "parentheses": 1
            }
        },
        "attr": {
            "349": false
        },
        "relationship": {
            "354": false
        },
        "entity": {
            "375": {
                "name": "array",
                "type": "unknown",
                "args_started": true,
                "arg_count": 4,
                "parentheses": 1
            }
        }
    },
    "\/hooks-api.php": {
        "Module Name: Hooks API\n\t\tAuthor:      J.D. Grimes\n\t\tAuthor URI:  http:\/\/codesymphony.co\/\n\t\tModule URI:  https:\/\/github.com\/WordPoints\/hooks-api\/\n\t\tVersion:     1.0.0\n\t\tLicense:     GPLv2+\n\t\tDescription: Provides a new API for hooks.": {
            "30": {
                "name": "WordPoints_Modules::register",
                "type": "unknown",
                "args_started": true,
                "arg_count": 0,
                "parentheses": 1
            }
        }
    },
    "\/includes\/class-un-installer.php": {
        "WordPoints_Hooks_API_Un_Installer": {
            "55": false
        }
    },
    "\/includes\/classes\/app.php": {
        "-": {
            "109": false
        }
    },
    "\/includes\/classes\/data\/type.php": {
        "error": {
            "106": false
        },
        "min": {
            "238": {
                "name": "array",
                "type": "unknown",
                "args_started": true,
                "arg_count": 0,
                "parentheses": 1
            }
        },
        "number": {
            "245": {
                "name": "array",
                "type": "unknown",
                "args_started": true,
                "arg_count": 2,
                "parentheses": 1
            }
        },
        "max": {
            "243": {
                "name": "array",
                "type": "unknown",
                "args_started": true,
                "arg_count": 0,
                "parentheses": 1
            }
        }
    },
    "\/includes\/classes\/entity\/post\/terms.php": {
        "ids": {
            "50": {
                "name": "array",
                "type": "unknown",
                "args_started": true,
                "arg_count": 0,
                "parentheses": 1
            }
        }
    },
    "\/includes\/classes\/hook\/condition\/entity\/array\/contains.php": {
        "min": {
            "68": {
                "name": "array",
                "type": "unknown",
                "args_started": true,
                "arg_count": 0,
                "parentheses": 1
            }
        },
        "number": {
            "76": {
                "name": "array",
                "type": "unknown",
                "args_started": true,
                "arg_count": 2,
                "parentheses": 1
            }
        },
        "max": {
            "74": {
                "name": "array",
                "type": "unknown",
                "args_started": true,
                "arg_count": 0,
                "parentheses": 1
            }
        }
    },
    "\/includes\/classes\/hook\/condition\/equals.php": {
        "text": {
            "31": {
                "name": "array",
                "type": "unknown",
                "args_started": true,
                "arg_count": 0,
                "parentheses": 1
            }
        }
    },
    "\/includes\/classes\/hook\/condition\/string\/contains.php": {
        "text": {
            "30": {
                "name": "array",
                "type": "unknown",
                "args_started": true,
                "arg_count": 0,
                "parentheses": 1
            }
        }
    },
    "\/includes\/classes\/hook\/extension\/conditions.php": {
        "entity": {
            "277": false
        }
    },
    "\/includes\/classes\/hook\/extension\/periods.php": {
        "-": {
            "331": false
        }
    },
    "\/includes\/classes\/hook\/reactor\/points.php": {
        "text": {
            "38": {
                "name": "array",
                "type": "unknown",
                "args_started": true,
                "arg_count": 0,
                "parentheses": 1
            }
        },
        "number": {
            "43": {
                "name": "array",
                "type": "unknown",
                "args_started": true,
                "arg_count": 1,
                "parentheses": 1
            }
        },
        "hidden": {
            "48": {
                "name": "array",
                "type": "unknown",
                "args_started": true,
                "arg_count": 1,
                "parentheses": 1
            }
        }
    },
    "\/includes\/classes\/hook\/router.php": {
        ",": {
            "200": false
        }
    },
    "\/includes\/functions.php": {
        "approved": {
            "111": {
                "name": "array",
                "type": "unknown",
                "args_started": true,
                "arg_count": 0,
                "parentheses": 1
            },
            "134": {
                "name": "array",
                "type": "unknown",
                "args_started": true,
                "arg_count": 0,
                "parentheses": 1
            }
        },
        "publish": {
            "147": {
                "name": "array",
                "type": "unknown",
                "args_started": true,
                "arg_count": 0,
                "parentheses": 1
            }
        },
        "wp": {
            "200": {
                "name": "array",
                "type": "unknown",
                "args_started": true,
                "arg_count": 0,
                "parentheses": 1
            }
        },
        "WordPoints_Hook_Arg": {
            "225": {
                "name": "array",
                "type": "unknown",
                "args_started": true,
                "arg_count": 0,
                "parentheses": 1
            }
        },
        "WordPoints_Hook_Arg_Current_User": {
            "238": {
                "name": "array",
                "type": "unknown",
                "args_started": true,
                "arg_count": 0,
                "parentheses": 1
            }
        },
        "post\\\\": {
            "442": {
                "name": "array",
                "type": "unknown",
                "args_started": true,
                "arg_count": 0,
                "parentheses": 1
            },
            "460": {
                "name": "array",
                "type": "unknown",
                "args_started": true,
                "arg_count": 0,
                "parentheses": 1
            }
        },
        "WordPoints_Hook_Arg_Dynamic": {
            "442": {
                "name": "array",
                "type": "unknown",
                "args_started": true,
                "arg_count": 0,
                "parentheses": 1
            },
            "460": {
                "name": "array",
                "type": "unknown",
                "args_started": true,
                "arg_count": 0,
                "parentheses": 1
            },
            "480": {
                "name": "array",
                "type": "unknown",
                "args_started": true,
                "arg_count": 0,
                "parentheses": 1
            }
        },
        "comment\\\\": {
            "480": {
                "name": "array",
                "type": "unknown",
                "args_started": true,
                "arg_count": 0,
                "parentheses": 1
            }
        }
    },
    "\/includes\/classes\/entity\/relationship\/dynamic.php": {
        "\\\\": {
            "31": false
        },
        "{}": {
            "34": false
        }
    },
    "\/includes\/classes\/hook\/event\/dynamic.php": {
        "\\\\": {
            "52": false
        }
    }
}